select_plus/__init__.py
select_plus/serializers.py
select_plus/ssp.py
select_plus/src/__init__.py
select_plus/src/aws/__init__.py
select_plus/src/aws/s3.py
select_plus/src/engine/__init__.py
select_plus/src/engine/base_engine.py
select_plus/src/engine/engine.py
select_plus/src/engine/parallel_engine.py
select_plus/src/engine/sequential_engine.py
select_plus/src/models/__init__.py
select_plus/src/models/models.py
select_plus/src/utils/__init__.py
select_plus/src/utils/cost.py
tests/__init__.py
tests/unit/__init__.py
tests/unit/test_base_engine.py
tests/unit/test_cost.py
tests/unit/test_engine.py
tests/unit/test_imports.py
tests/unit/test_models.py
tests/unit/test_parallel_engine.py
tests/unit/test_s3.py
tests/unit/test_sequential_engine.py
tests/unit/test_ssp.py
tests/util/__init__.py
tests/util/test_wrapper.py
s3select_plus-1.0.3.dist-info/METADATA
s3select_plus-1.0.3.dist-info/WHEEL
s3select_plus-1.0.3.dist-info/top_level.txt
s3select_plus-1.0.3.dist-info/RECORD
