Metadata-Version: 2.1
Name: s3select-plus
Version: 1.0.3
Summary: S3 select parallel package
Home-page: https://github.com/gabriel-oana/s3select_plus
Author: Gabriel Oana
Author-email: gabriel.oana91@gmail.com
Classifier: Programming Language :: Python :: 3.7
Classifier: Programming Language :: Python :: 3.8
Classifier: Programming Language :: Python :: 3.9
Classifier: Programming Language :: Python :: 3.10
Classifier: License :: OSI Approved :: MIT License
Classifier: Operating System :: OS Independent
Requires-Dist: boto3 (>=1.24.75)
Requires-Dist: tqdm (>=4.64.1)
